umovme/__init__.py
umovme/__main__.py
umovme/api.py
umovme/cli.py
umovme/client.py
umovme/resources/__init__.py
umovme/resources/base.py
umovme/resources/exceptions.py
umovme-0.0.2.dist-info/AUTHORS.rst
umovme-0.0.2.dist-info/LICENSE
umovme-0.0.2.dist-info/METADATA
umovme-0.0.2.dist-info/WHEEL
umovme-0.0.2.dist-info/entry_points.txt
umovme-0.0.2.dist-info/top_level.txt
umovme-0.0.2.dist-info/RECORD
